[
  {
    "updated_at": "2026-06-01 10:01:46 UTC",
    "latest_event_date": "2026-06-01",
    "public_claim_count": 227,
    "public_source_count": 117,
    "public_source_analysis_count": 117,
    "public_analysis_note_count": 0,
    "candidate_analysis_count": 14,
    "comparison_report_count": 1,
    "editorial_package_count": 17,
    "candidate_policy_dossier_count": 6,
    "comparison_essay_count": 10,
    "source_text_file_count": 39,
    "manual_source_registry_count": 205,
    "promoted_manual_source_count": 36,
    "pending_manual_source_count": 119,
    "program_document_count": 6,
    "primary_program_document_count": 6,
    "source_packet_count": 117,
    "extraction_result_count": 117,
    "pipeline_mode": "structured_extraction_auto",
    "validation_status": "pass"
  }
]
